dmxfy/__init__.py
dmxfy/cli/__init__.py
dmxfy/cli/cli.py
dmxfy/client/__init__.py
dmxfy/client/client.py
dmxfy/config/__init__.py
dmxfy/config/config.py
dmxfy/exceptions/__init__.py
dmxfy/exceptions/exceptions.py
dmxfy/languages/__init__.py
dmxfy/languages/languages.py
dmxfy/utils/__init__.py
dmxfy-0.6.1.dist-info/METADATA
dmxfy-0.6.1.dist-info/WHEEL
dmxfy-0.6.1.dist-info/entry_points.txt
dmxfy-0.6.1.dist-info/RECORD
