Metadata-Version: 2.4
Name: dmxfy
Version: 0.6.1
Summary: 大语言模型翻译器终端
Author-email: workspc <wokspc@gmail.com>
Requires-Python: >=3.11
Requires-Dist: prompt-toolkit>=3.0.0
Provides-Extra: test
Requires-Dist: pytest-cov>=4.1.0; extra == 'test'
Requires-Dist: pytest<8.0.0,>=7.4.3; extra == 'test'
